ligo/raven/__init__.py
ligo/raven/gracedb_events.py
ligo/raven/search.py
ligo/raven/tests/FAR_study.py
ligo/raven/tests/FAR_subgrb_study.py
ligo/raven/tests/__init__.py
ligo/raven/tests/mock_gracedb_rest.py
ligo/raven/tests/mock_gracedb_sdk.py
ligo/raven/tests/test_overlap_integral.py
ligo/raven/tests/test_raven_search.py
ligo/raven/tests/test_search_window.py
ligo_raven-3.3.data/scripts/raven_calc_signif_gracedb
ligo_raven-3.3.data/scripts/raven_coinc_far
ligo_raven-3.3.data/scripts/raven_query
ligo_raven-3.3.data/scripts/raven_search
ligo_raven-3.3.data/scripts/raven_skymap_overlap
ligo_raven-3.3.dist-info/licenses/COPYING
ligo_raven-3.3.dist-info/METADATA
ligo_raven-3.3.dist-info/WHEEL
ligo_raven-3.3.dist-info/top_level.txt
ligo_raven-3.3.dist-info/RECORD
